CHANGES.txt
MANIFEST.in
README.rst
setup.py
isotoma/__init__.py
isotoma.recipe.postdeploy.egg-info/PKG-INFO
isotoma.recipe.postdeploy.egg-info/SOURCES.txt
isotoma.recipe.postdeploy.egg-info/dependency_links.txt
isotoma.recipe.postdeploy.egg-info/entry_points.txt
isotoma.recipe.postdeploy.egg-info/namespace_packages.txt
isotoma.recipe.postdeploy.egg-info/not-zip-safe
isotoma.recipe.postdeploy.egg-info/requires.txt
isotoma.recipe.postdeploy.egg-info/top_level.txt
isotoma/recipe/__init__.py
isotoma/recipe/postdeploy/__init__.py
isotoma/recipe/postdeploy/history.py
isotoma/recipe/postdeploy/recipe.py
isotoma/recipe/postdeploy/script.py
isotoma/recipe/postdeploy/templates/buildout.yay.j2
isotoma/recipe/postdeploy/templates/history.yay.j2