Metadata-Version: 1.0
Name: isotoma.recipe.postdeploy
Version: 0.0.1
Summary: Buildout recipes for postdeploy.
Home-page: http://pypi.python.org/pypi/isotoma.recipe.postdeploy
Author: John Carr
Author-email: john.carr@isotoma.com
License: Apache Software License
Keywords: proxy buildout postdeploy
Platform: UNKNOWN
Classifier: Framework :: Buildout
Classifier: Framework :: Buildout :: Recipe
Classifier: Intended Audience :: System Administrators
Classifier: Operating System :: POSIX
Classifier: License :: OSI Approved :: Apache Software License
